CHANGES.rst
LICENSE
MANIFEST.in
README.rst
requirements.txt
setup.py
django_mc/__init__.py
django_mc/admin.py
django_mc/apps.py
django_mc/migration_operations.py
django_mc/mixins.py
django_mc/models.py
django_mc/settings.py
django_mc/utils.py
django_mc/views.py
django_mc.egg-info/PKG-INFO
django_mc.egg-info/SOURCES.txt
django_mc.egg-info/dependency_links.txt
django_mc.egg-info/not-zip-safe
django_mc.egg-info/requires.txt
django_mc.egg-info/top_level.txt
django_mc/generic/__init__.py
django_mc/generic/pageview.py
django_mc/link/__init__.py
django_mc/link/apps.py
django_mc/link/autodiscover.py
django_mc/link/fields.py
django_mc/link/models.py
django_mc/link/pattern.py
django_mc/link/registry.py
django_mc/link/resolvers.py
django_mc/link/text_filters.py
django_mc/link/migrations/0001_initial.py
django_mc/link/migrations/__init__.py
django_mc/link/templatetags/__init__.py
django_mc/link/templatetags/django_mc_link_tags.py
django_mc/migrations/0001_initial.py
django_mc/migrations/0002_add_layoutregioncomponent_model.py
django_mc/migrations/0003_add_region_position_field.py
django_mc/migrations/__init__.py
django_mc/templatetags/__init__.py
django_mc/templatetags/django_mc_component_tags.py
django_mc/templatetags/django_mc_include_tags.py
django_mc/utils/__init__.py
django_mc/utils/functional.py
tests/__init__.py
tests/requirements.txt
tests/settings.py
tests/test_imports.py