Metadata-Version: 1.1
Name: django-mc
Version: 0.1.0
Summary: A foundational structure for CMS systems. Helps you to create page models, components (individual content blocks to build up pages) and to attach components to pages.
Home-page: https://git.team23.de/team23/django_mc
Author: David Danier
Author-email: david.danier@team23.de
License: BSD licence, see LICENSE file
Platform: UNKNOWN
Classifier: Development Status :: 4 - Beta
Classifier: Environment :: Web Environment
Classifier: Framework :: Django
Classifier: Framework :: Django :: 1.8
Classifier: Intended Audience :: Developers
Classifier: License :: OSI Approved :: BSD License
Classifier: Natural Language :: English
Classifier: Programming Language :: Python
Classifier: Programming Language :: Python :: 2
Classifier: Programming Language :: Python :: 2.7
